<annotation>
	<folder>promos</folder>
	<filename>162.jpg</filename>
	<path>/Users/tomas/Documents/future/datasets/promos/162.jpg</path>
	<source>
		<database>Unknown</database>
	</source>
	<size>
		<width>898</width>
		<height>1254</height>
		<depth>3</depth>
	</size>
	<segmented>0</segmented>
	<object>
		<name>product</name>
		<pose>Unspecified</pose>
		<truncated>0</truncated>
		<difficult>0</difficult>
		<bndbox>
			<xmin>8</xmin>
			<ymin>492</ymin>
			<xmax>470</xmax>
			<ymax>878</ymax>
		</bndbox>
	</object>
	<object>
		<name>product</name>
		<pose>Unspecified</pose>
		<truncated>0</truncated>
		<difficult>0</difficult>
		<bndbox>
			<xmin>17</xmin>
			<ymin>890</ymin>
			<xmax>474</xmax>
			<ymax>1199</ymax>
		</bndbox>
	</object>
	<object>
		<name>product</name>
		<pose>Unspecified</pose>
		<truncated>0</truncated>
		<difficult>0</difficult>
		<bndbox>
			<xmin>483</xmin>
			<ymin>878</ymin>
			<xmax>892</xmax>
			<ymax>1198</ymax>
		</bndbox>
	</object>
	<object>
		<name>product</name>
		<pose>Unspecified</pose>
		<truncated>0</truncated>
		<difficult>0</difficult>
		<bndbox>
			<xmin>464</xmin>
			<ymin>506</ymin>
			<xmax>884</xmax>
			<ymax>873</ymax>
		</bndbox>
	</object>
</annotation>
